solarwinds_apm/__init__.py
solarwinds_apm/apm_config.py
solarwinds_apm/apm_constants.py
solarwinds_apm/apm_logging.py
solarwinds_apm/configurator.py
solarwinds_apm/distro.py
solarwinds_apm/k8s.py
solarwinds_apm/propagator.py
solarwinds_apm/response_propagator.py
solarwinds_apm/sampler.py
solarwinds_apm/traceoptions.py
solarwinds_apm/tracer_provider.py
solarwinds_apm/uams.py
solarwinds_apm/version.py
solarwinds_apm/w3c_transformer.py
solarwinds_apm/api/__init__.py
solarwinds_apm/oboe/__init__.py
solarwinds_apm/oboe/configuration.py
solarwinds_apm/oboe/dice.py
solarwinds_apm/oboe/http_sampler.py
solarwinds_apm/oboe/json_sampler.py
solarwinds_apm/oboe/metrics.py
solarwinds_apm/oboe/oboe_sampler.py
solarwinds_apm/oboe/sampler.py
solarwinds_apm/oboe/settings.py
solarwinds_apm/oboe/token_bucket.py
solarwinds_apm/oboe/trace_options.py
solarwinds_apm/oboe/transaction_name_calculator.py
solarwinds_apm/oboe/transaction_name_pool.py
solarwinds_apm/semconv/__init__.py
solarwinds_apm/semconv/trace/__init__.py
solarwinds_apm/trace/__init__.py
solarwinds_apm/trace/response_time_processor.py
solarwinds_apm/trace/serviceentry_processor.py
solarwinds_apm-5.2.1.dist-info/licenses/LICENSE
solarwinds_apm-5.2.1.dist-info/METADATA
solarwinds_apm-5.2.1.dist-info/WHEEL
solarwinds_apm-5.2.1.dist-info/entry_points.txt
solarwinds_apm-5.2.1.dist-info/top_level.txt
solarwinds_apm-5.2.1.dist-info/RECORD
