Metadata-Version: 2.4
Name: solarwinds_apm
Version: 5.2.1
Summary: OpenTelemetry custom distro to connect to SolarWinds
Author-email: "SolarWinds, LLC" <SWO-support@solarwinds.com>
Maintainer-email: Tammy Baylis <tammy.baylis@solarwinds.com>
License:                                  Apache License
Project-URL: Homepage, https://www.solarwinds.com/solarwinds-observability/use-cases/python-performance-monitoring
Project-URL: Download, https://pypi.org/project/solarwinds-apm/
Project-URL: Documentation, https://documentation.solarwinds.com/en/success_center/observability/content/configure/services/python/python.htm
Project-URL: Changelog, https://documentation.solarwinds.com/en/success_center/observability/content/release_notes/python-release-notes.htm
Keywords: solarwinds_apm,appoptics_apm,traceview,tracelytics,oboe,instrumentation,performance,opentelemetry,observability
Classifier: Typing :: Typed
Classifier: Development Status :: 5 - Production/Stable
Classifier: Intended Audience :: Developers
Classifier: Intended Audience :: Information Technology
Requires-Python: >=3.9
License-File: LICENSE
Requires-Dist: opentelemetry-api==1.39.1
Requires-Dist: opentelemetry-sdk==1.39.1
Requires-Dist: opentelemetry-exporter-otlp==1.39.1
Requires-Dist: opentelemetry-instrumentation==0.60b1
Requires-Dist: opentelemetry-instrumentation-logging==0.60b1
Requires-Dist: opentelemetry-sdk-extension-aws==2.1.0
Requires-Dist: opentelemetry-resource-detector-azure==0.1.5
Requires-Dist: opentelemetry-resource-detector-containerid==0.60b1
Dynamic: license-file
